stad/__init__.py
stad-2.0.1.dist-info/LICENSE
stad-2.0.1.dist-info/METADATA
stad-2.0.1.dist-info/WHEEL
stad-2.0.1.dist-info/top_level.txt
stad-2.0.1.dist-info/RECORD
