Metadata-Version: 2.1
Name: stad
Version: 2.0.1
Summary: Dimensionality reduction through Simplified Topological Abstraction of Data
Home-page: https://github.com/vda-lab/pySTAD
Author: Jan Aerts
Author-email: jan.aerts@uhasselt.be
License: UNKNOWN
Platform: UNKNOWN
Classifier: Programming Language :: Python :: 3
Classifier: License :: OSI Approved :: MIT License
Classifier: Operating System :: OS Independent
Classifier: Topic :: Scientific/Engineering :: Visualization
Classifier: Topic :: Scientific/Engineering
Requires-Python: >=3
